scikit_bio-0.7.0.dist-info/RECORD
scikit_bio-0.7.0.dist-info/WHEEL
scikit_bio-0.7.0.dist-info/top_level.txt
scikit_bio-0.7.0.dist-info/METADATA
scikit_bio-0.7.0.dist-info/licenses/LICENSE.txt
skbio/_base.py
skbio/__init__.py
skbio/test.py
skbio/workflow.py
skbio/_config.py
skbio/tree/_majority_rule.py
skbio/tree/_nj.py
skbio/tree/_me.py
skbio/tree/_exception.py
skbio/tree/_upgma.py
skbio/tree/_c_me.pyx
skbio/tree/__init__.py
skbio/tree/_c_nj.pyx
skbio/tree/_c_me.cpython-310-darwin.so
skbio/tree/_c_nj.cpython-310-darwin.so
skbio/tree/_c_me.c
skbio/tree/_tree.py
skbio/tree/_utils.py
skbio/tree/_compare.py
skbio/tree/_c_nj.c
skbio/tree/tests/test_me.py
skbio/tree/tests/test_utils.py
skbio/tree/tests/test_tree.py
skbio/tree/tests/__init__.py
skbio/tree/tests/test_nj.py
skbio/tree/tests/test_upgma.py
skbio/tree/tests/test_compare.py
skbio/tree/tests/test_majority_rule.py
skbio/util/_gpu.py
skbio/util/_decorator.py
skbio/util/_typing.py
skbio/util/_exception.py
skbio/util/__init__.py
skbio/util/_plotting.py
skbio/util/_warning.py
skbio/util/_random.py
skbio/util/_optionals.py
skbio/util/_array.py
skbio/util/_testing.py
skbio/util/_docstring.py
skbio/util/_misc.py
skbio/util/tests/test_plotting.py
skbio/util/tests/test_misc.py
skbio/util/tests/test_docstring.py
skbio/util/tests/test_warning.py
skbio/util/tests/test_array.py
skbio/util/tests/__init__.py
skbio/util/tests/test_optionals.py
skbio/util/tests/test_random.py
skbio/util/tests/test_decorator.py
skbio/util/tests/test_testing.py
skbio/io/_fileobject.py
skbio/io/registry.py
skbio/io/util.py
skbio/io/_exception.py
skbio/io/__init__.py
skbio/io/_warning.py
skbio/io/descriptors.py
skbio/io/_iosources.py
skbio/io/tests/test_registry.py
skbio/io/tests/test_iosources.py
skbio/io/tests/__init__.py
skbio/io/tests/test_util.py
skbio/io/tests/data/real_file_2
skbio/io/tests/data/big5_file.gz
skbio/io/tests/data/big5_file.bz2
skbio/io/tests/data/real_file
skbio/io/tests/data/example_file
skbio/io/tests/data/big5_file
skbio/io/tests/data/example_file.bz2
skbio/io/tests/data/example_file.gz
skbio/io/format/newick.py
skbio/io/format/_base.py
