Metadata-Version: 2.4
Name: scikit-bio
Version: 0.7.0
Summary: Data structures, algorithms and educational resources for bioinformatics.
Author-email: scikit-bio development team <qiyunzhu@gmail.com>
Maintainer-email: scikit-bio development team <qiyunzhu@gmail.com>
Project-URL: Homepage, https://scikit.bio
Project-URL: Documentation, https://scikit.bio/docs/latest/
Project-URL: Repository, https://github.com/scikit-bio/scikit-bio
Project-URL: Issues, https://github.com/scikit-bio/scikit-bio/issues
Classifier: Development Status :: 4 - Beta
Classifier: License :: OSI Approved :: BSD License
Classifier: Topic :: Software Development :: Libraries
Classifier: Topic :: Scientific/Engineering
Classifier: Topic :: Scientific/Engineering :: Bio-Informatics
Classifier: Programming Language :: Python :: 3
Classifier: Programming Language :: Python :: 3 :: Only
Classifier: Programming Language :: Python :: 3.9
Classifier: Programming Language :: Python :: 3.10
Classifier: Programming Language :: Python :: 3.11
Classifier: Programming Language :: Python :: 3.12
Classifier: Programming Language :: Python :: 3.13
Classifier: Operating System :: Unix
Classifier: Operating System :: POSIX
Classifier: Operating System :: MacOS :: MacOS X
Classifier: Operating System :: Microsoft :: Windows
Requires-Python: >=3.9
License-File: LICENSE.txt
Requires-Dist: requests>=2.20.0
Requires-Dist: decorator>=3.4.2
Requires-Dist: natsort>=4.0.3
Requires-Dist: numpy>=1.17.0
Requires-Dist: pandas>=1.5.0
Requires-Dist: scipy>=1.9.0
Requires-Dist: h5py>=3.6.0
Requires-Dist: biom-format>=2.1.16
Requires-Dist: statsmodels>=0.14.0
Requires-Dist: patsy>=0.5.0
Requires-Dist: array-api-compat>=1.3
Provides-Extra: test
Requires-Dist: pytest; extra == "test"
Requires-Dist: coverage; extra == "test"
Requires-Dist: responses; extra == "test"
Requires-Dist: matplotlib; extra == "test"
Provides-Extra: docs
Requires-Dist: sphinx; extra == "docs"
Requires-Dist: sphinx-design; extra == "docs"
Requires-Dist: sphinx-copybutton; extra == "docs"
Requires-Dist: pydata-sphinx-theme; extra == "docs"
Requires-Dist: sphinxcontrib-youtube; extra == "docs"
Requires-Dist: sphinx-sitemap; extra == "docs"
Requires-Dist: numpydoc; extra == "docs"
Requires-Dist: matplotlib; extra == "docs"
Requires-Dist: statsmodels; extra == "docs"
Requires-Dist: patsy; extra == "docs"
Provides-Extra: lint
Requires-Dist: check-manifest; extra == "lint"
Requires-Dist: python-dateutil; extra == "lint"
Requires-Dist: numpy; extra == "lint"
Requires-Dist: ruff; extra == "lint"
Requires-Dist: pre-commit; extra == "lint"
Provides-Extra: dev
Requires-Dist: pytest; extra == "dev"
Requires-Dist: coverage; extra == "dev"
Requires-Dist: responses; extra == "dev"
Requires-Dist: matplotlib; extra == "dev"
Requires-Dist: sphinx; extra == "dev"
Requires-Dist: sphinx-design; extra == "dev"
Requires-Dist: sphinx-copybutton; extra == "dev"
Requires-Dist: pydata-sphinx-theme; extra == "dev"
Requires-Dist: sphinxcontrib-youtube; extra == "dev"
Requires-Dist: sphinx-sitemap; extra == "dev"
Requires-Dist: numpydoc; extra == "dev"
Requires-Dist: statsmodels; extra == "dev"
Requires-Dist: patsy; extra == "dev"
Requires-Dist: check-manifest; extra == "dev"
Requires-Dist: python-dateutil; extra == "dev"
Requires-Dist: numpy; extra == "dev"
Requires-Dist: ruff; extra == "dev"
Requires-Dist: pre-commit; extra == "dev"
Dynamic: license-file
